cotat/__init__.py
cotat/cotat.py
cotat/resources/button.js
cotat/resources/instructions.html
cotat/resources/search.js
cotat/tests/__init__.py
cotat/tests/test_cotat.py
cotat-0.2.0.dist-info/LICENSE
cotat-0.2.0.dist-info/METADATA
cotat-0.2.0.dist-info/WHEEL
cotat-0.2.0.dist-info/top_level.txt
cotat-0.2.0.dist-info/RECORD
