Metadata-Version: 2.1
Name: cotat
Version: 0.2.0
Home-page: https://github.com/cornell-covid-modeling/cotat
Author: Cornell Covid Modeling Team
Author-email: hwr26@cornell.edu
Classifier: Programming Language :: Python :: 3.5
Classifier: Programming Language :: Python :: 3.6
Classifier: Programming Language :: Python :: 3.7
Classifier: Programming Language :: Python :: 3.8
Classifier: Programming Language :: Python :: 3.9
Classifier: Programming Language :: Python :: 3.10
Classifier: License :: OSI Approved :: MIT License
Classifier: Operating System :: OS Independent
Requires-Python: >=3.5
License-File: LICENSE
Requires-Dist: numpy (>=1.20)
Requires-Dist: pandas (>=1.2)
Requires-Dist: networkx (>=2.5)
Requires-Dist: bokeh (>=3)
Provides-Extra: dev
Requires-Dist: pytest (>=5) ; extra == 'dev'
Requires-Dist: mock (>=3) ; extra == 'dev'
Requires-Dist: coverage (>=4.5) ; extra == 'dev'
Requires-Dist: tox (>=3) ; extra == 'dev'
Requires-Dist: flake8 (>=3.9) ; extra == 'dev'
